danticsql/__init__.py
danticsql/main.py
danticsql-0.1.0.dist-info/METADATA
danticsql-0.1.0.dist-info/WHEEL
danticsql-0.1.0.dist-info/licenses/LICENSE
danticsql-0.1.0.dist-info/RECORD
