Metadata-Version: 2.4
Name: danticsql
Version: 0.1.0
Summary: A powerful Python utility designed to efficiently reconstruct nested SQLModel object graphs from a flat Pandas DataFrame
Project-URL: Homepage, https://github.com/saya-ashen/DanticSQL
Project-URL: Issues, https://github.com/saya-ashen/DanticSQL/issues
Author-email: Saya Ashen <c3313433633@gmail.com>
License: MIT License
License-File: LICENSE
Requires-Python: >=3.12
Requires-Dist: pandas>=2.3.0
Requires-Dist: pydantic>=2.11.7
Requires-Dist: sqlmodel>=0.0.24
